pyivm/__init__.py
pyivm/ivm/__init__.py
pyivm/ivm/calinski_harabasz.py
pyivm/ivm/davies_bouldin.py
pyivm/ivm/dunn.py
pyivm/ivm/i_index.py
pyivm/ivm/silhouette.py
pyivm/ivm/utils.py
pyivm/ivm/xie_beni.py
pyivm-0.1.0.dist-info/LICENSE
pyivm-0.1.0.dist-info/METADATA
pyivm-0.1.0.dist-info/WHEEL
pyivm-0.1.0.dist-info/RECORD
