Metadata-Version: 2.1
Name: pyivm
Version: 0.1.0
Summary: Python library for clustering quality index metrics with original and adjusted forms
Home-page: https://github.com/hj-n/pyivm
Keywords: clustering,metrics,machine-learning,data-science,evaluation
Author: Hyeon Jeon
Author-email: hj@hcil.snu.ac.kr
Requires-Python: >=3.9,<4.0
Classifier: Development Status :: 4 - Beta
Classifier: Intended Audience :: Science/Research
Classifier: License :: OSI Approved :: MIT License
Classifier: Programming Language :: Python :: 3
Classifier: Programming Language :: Python :: 3.9
Classifier: Programming Language :: Python :: 3.10
Classifier: Programming Language :: Python :: 3.11
Classifier: Programming Language :: Python :: 3.12
Classifier: Programming Language :: Python :: 3.13
Classifier: Topic :: Scientific/Engineering :: Artificial Intelligence
Classifier: Topic :: Software Development :: Libraries :: Python Modules
Requires-Dist: numpy (>=1.20.0,<2.0.0)
Requires-Dist: pandas (>=1.3.0,<2.0.0)
Requires-Dist: scikit-learn (>=1.0.0,<2.0.0)
Requires-Dist: scipy (>=1.7.0,<2.0.0)
Project-URL: Repository, https://github.com/hj-n/pyivm
